deker_tools/__init__.py
deker_tools/data.py
deker_tools/path.py
deker_tools/slices.py
deker_tools/time.py
deker_tools-1.0.0b0.dist-info/LICENSE
deker_tools-1.0.0b0.dist-info/METADATA
deker_tools-1.0.0b0.dist-info/WHEEL
deker_tools-1.0.0b0.dist-info/top_level.txt
deker_tools-1.0.0b0.dist-info/RECORD
